{"data":[{"xs":{"x":402,"y":602},"ys":{"freq":120}},
         {"xs":{"x":901,"y":586},"ys":{"freq":220}},
         {"xs":{"x":214,"y":1013},"ys":{"freq":360}},
         {"xs":{"x":383,"y":231},"ys":{"freq":80}},
         {"xs":{"x":2,"y":163},"ys":{"freq":360}},
         {"xs":{"x":18,"y":160},"ys":{"freq":460}},
         {"xs":{"x":165,"y":153},"ys":{"freq":880}},
         {"xs":{"x":633,"y":595},"ys":{"freq":20}},
         {"xs":{"x":613,"y":595},"ys":{"freq":340}},
         {"xs":{"x":1420,"y":355},"ys":{"freq":100}},
         {"xs":{"x":1420,"y":355},"ys":{"freq":780}},
         {"xs":{"x":200,"y":500},"ys":{"freq":460}},
         {"xs":{"x":100,"y":600},"ys":{"freq":880}},
         {"xs":{"x":800,"y":200},"ys":{"freq":20}},
         {"xs":{"x":220,"y":350},"ys":{"freq":340}},
         {"xs":{"x":1220,"y":140},"ys":{"freq":100}},
         {"xs":{"x":560,"y":1080},"ys":{"freq":780}},
         {"xs":{"x":20,"y":60},"ys":{"freq":88}},
         {"xs":{"x":80,"y":20},"ys":{"freq":20}},
         {"xs":{"x":22,"y":35},"ys":{"freq":34}},
         {"xs":{"x":12,"y":14},"ys":{"freq":10}},
         {"xs":{"x":56,"y":80},"ys":{"freq":78}}
        ]}
